autoparallel/__init__.py
autoparallel/decorator.py
autoparallel/py.typed
autoparallel-0.2.0.dist-info/licenses/LICENSE
autoparallel-0.2.0.dist-info/METADATA
autoparallel-0.2.0.dist-info/WHEEL
autoparallel-0.2.0.dist-info/top_level.txt
autoparallel-0.2.0.dist-info/RECORD
