Metadata-Version: 2.4
Name: autoparallel
Version: 0.2.0
Summary: Automatic parallel execution decorator using joblib
Author-email: Navaneeth <kamballu@ualberta.ca>
License: MIT
Project-URL: Homepage, https://github.com/kamballu/autoparallel
Project-URL: Repository, https://github.com/kamballu/autoparallel
Project-URL: Issues, https://github.com/kamballu/autoparallel/issues
Keywords: parallel,multiprocessing,decorator,joblib,automatic
Classifier: Development Status :: 4 - Beta
Classifier: Intended Audience :: Developers
Classifier: License :: OSI Approved :: MIT License
Classifier: Programming Language :: Python :: 3
Classifier: Programming Language :: Python :: 3.8
Classifier: Programming Language :: Python :: 3.9
Classifier: Programming Language :: Python :: 3.10
Classifier: Programming Language :: Python :: 3.11
Classifier: Programming Language :: Python :: 3.12
Classifier: Topic :: Software Development :: Libraries :: Python Modules
Requires-Python: >=3.8
License-File: LICENSE
Requires-Dist: joblib>=1.3.0
Provides-Extra: dev
Requires-Dist: pytest>=7.0; extra == "dev"
Requires-Dist: pytest-cov>=4.0; extra == "dev"
Requires-Dist: black>=23.0; extra == "dev"
Requires-Dist: mypy>=1.0; extra == "dev"
Requires-Dist: ruff>=0.1.0; extra == "dev"
Dynamic: license-file
